{
  "metadata": {
    "packet": "batch-29",
    "purpose": "Expected outcomes for E2E Tally to Review Queue testing",
    "created_at": "2026-07-06T19:46:11Z",
    "pass_rule": "A test passes when the webhook accepts/rejects with the expected status and the classification/review posture matches the expected tier/risk/manual-review direction. Exact score values may vary while scoring logic is tuned."
  },
  "expected_results": [
    {
      "case_id": "tier1-strategic-partner",
      "sequence": 1,
      "expected_http_status": 202,
      "expected_partner_type": "strategic_partner",
      "expected_tier": "tier_1",
      "expected_manual_review_required": true,
      "expected_risk_level": "low",
      "expected_review_queue_status": "needs_review",
      "expected_recommended_decision": "fast_track_after_operator_review",
      "expected_storage_behavior": "mock_or_sandbox_only",
      "expected_log_policy": "log case_id/status/request_id only; do not log raw payload or real PII",
      "operator_gate": "manual review required before activation or outreach"
    },
    {
      "case_id": "tier2-broker",
      "sequence": 2,
      "expected_http_status": 202,
      "expected_partner_type": "funding_broker",
      "expected_tier": "tier_2",
      "expected_manual_review_required": true,
      "expected_risk_level": "medium",
      "expected_review_queue_status": "needs_review",
      "expected_recommended_decision": "conditional_approval_review",
      "expected_storage_behavior": "mock_or_sandbox_only",
      "expected_log_policy": "log case_id/status/request_id only; do not log raw payload or real PII",
      "operator_gate": "manual review required before activation or outreach"
    },
    {
      "case_id": "cpa-bookkeeper",
      "sequence": 3,
      "expected_http_status": 202,
      "expected_partner_type": "cpa_bookkeeper",
      "expected_tier": "tier_2",
      "expected_manual_review_required": true,
      "expected_risk_level": "low",
      "expected_review_queue_status": "needs_review",
      "expected_recommended_decision": "approve_after_manual_review",
      "expected_storage_behavior": "mock_or_sandbox_only",
      "expected_log_policy": "log case_id/status/request_id only; do not log raw payload or real PII",
      "operator_gate": "manual review required before activation or outreach"
    },
    {
      "case_id": "business-attorney",
      "sequence": 4,
      "expected_http_status": 202,
      "expected_partner_type": "business_attorney",
      "expected_tier": "tier_2",
      "expected_manual_review_required": true,
      "expected_risk_level": "low",
      "expected_review_queue_status": "needs_review",
      "expected_recommended_decision": "approve_after_manual_review",
      "expected_storage_behavior": "mock_or_sandbox_only",
      "expected_log_policy": "log case_id/status/request_id only; do not log raw payload or real PII",
      "operator_gate": "manual review required before activation or outreach"
    },
    {
      "case_id": "veteran-community-connector",
      "sequence": 5,
      "expected_http_status": 202,
      "expected_partner_type": "community_connector",
      "expected_tier": "tier_3",
      "expected_manual_review_required": true,
      "expected_risk_level": "low",
      "expected_review_queue_status": "needs_review",
      "expected_recommended_decision": "nurture_and_resource_path",
      "expected_storage_behavior": "mock_or_sandbox_only",
      "expected_log_policy": "log case_id/status/request_id only; do not log raw payload or real PII",
      "operator_gate": "manual review required before activation or outreach"
    },
    {
      "case_id": "content-creator-affiliate",
      "sequence": 6,
      "expected_http_status": 202,
      "expected_partner_type": "affiliate_partner",
      "expected_tier": "tier_3",
      "expected_manual_review_required": true,
      "expected_risk_level": "medium",
      "expected_review_queue_status": "needs_review",
      "expected_recommended_decision": "approve_after_disclosure_review",
      "expected_storage_behavior": "mock_or_sandbox_only",
      "expected_log_policy": "log case_id/status/request_id only; do not log raw payload or real PII",
      "operator_gate": "manual review required before activation or outreach"
    },
    {
      "case_id": "low-info-signup",
      "sequence": 7,
      "expected_http_status": 202,
      "expected_partner_type": "unknown_or_low_info",
      "expected_tier": "needs_info",
      "expected_manual_review_required": true,
      "expected_risk_level": "medium",
      "expected_review_queue_status": "needs_info",
      "expected_recommended_decision": "request_more_information",
      "expected_storage_behavior": "mock_or_sandbox_only",
      "expected_log_policy": "log case_id/status/request_id only; do not log raw payload or real PII",
      "operator_gate": "manual review required before activation or outreach"
    },
    {
      "case_id": "high-risk-lead-seller",
      "sequence": 8,
      "expected_http_status": 202,
      "expected_partner_type": "lead_seller",
      "expected_tier": "reject_or_watchlist",
      "expected_manual_review_required": true,
      "expected_risk_level": "high",
      "expected_review_queue_status": "blocked_pending_review",
      "expected_recommended_decision": "do_not_activate_without_operator_review",
      "expected_storage_behavior": "mock_or_sandbox_only",
      "expected_log_policy": "log case_id/status/request_id only; do not log raw payload or real PII",
      "operator_gate": "manual review required before activation or outreach"
    },
    {
      "case_id": "duplicate-submission",
      "sequence": 9,
      "expected_http_status": 202,
      "expected_partner_type": "funding_broker",
      "expected_tier": "tier_2",
      "expected_manual_review_required": true,
      "expected_risk_level": "medium",
      "expected_review_queue_status": "duplicate_review",
      "expected_recommended_decision": "do_not_create_duplicate_without_operator_review",
      "expected_storage_behavior": "mock_or_sandbox_only",
      "expected_log_policy": "log case_id/status/request_id only; do not log raw payload or real PII",
      "operator_gate": "manual review required before activation or outreach"
    },
    {
      "case_id": "malformed-payload",
      "sequence": 10,
      "expected_http_status": 400,
      "expected_partner_type": null,
      "expected_tier": null,
      "expected_manual_review_required": true,
      "expected_risk_level": "n/a",
      "expected_review_queue_status": "not_created",
      "expected_recommended_decision": "reject_request_and_log_safe_error",
      "expected_storage_behavior": "mock_or_sandbox_only",
      "expected_log_policy": "log case_id/status/request_id only; do not log raw payload or real PII",
      "operator_gate": "manual review required before activation or outreach"
    }
  ]
}
